LICENSE
MANIFEST.in
README.rst
setup.cfg
setup.py
django_skeleton_setup.egg-info/PKG-INFO
django_skeleton_setup.egg-info/SOURCES.txt
django_skeleton_setup.egg-info/dependency_links.txt
django_skeleton_setup.egg-info/requires.txt
django_skeleton_setup.egg-info/top_level.txt
skeleton_setup/__init__.py
skeleton_setup/apps.py
skeleton_setup/backends.py
skeleton_setup/env_local.env
skeleton_setup/models.py
skeleton_setup/settings_common.py
skeleton_setup/settings_local.py
skeleton_setup/settings_production.py
skeleton_setup/__pycache__/__init__.cpython-36.pyc
skeleton_setup/__pycache__/models.cpython-36.pyc
skeleton_setup/conf/app_template/__init__.py-tpl
skeleton_setup/conf/app_template/admin.py-tpl
skeleton_setup/conf/app_template/apps.py-tpl
skeleton_setup/conf/app_template/forms.py-tpl
skeleton_setup/conf/app_template/model_managers.py-tpl
skeleton_setup/conf/app_template/models.py-tpl
skeleton_setup/conf/app_template/signals.py-tpl
skeleton_setup/conf/app_template/urls.py-tpl
skeleton_setup/conf/app_template/utils.py-tpl
skeleton_setup/conf/app_template/views.py-tpl
skeleton_setup/conf/app_template/api/__init__.py-tpl
skeleton_setup/conf/app_template/api/urls.py-tpl
skeleton_setup/conf/app_template/api/views.py-tpl
skeleton_setup/conf/app_template/migrations/__init__.py-tpl
skeleton_setup/conf/app_template/serializers/__init__.py-tpl
skeleton_setup/conf/app_template/services/__init__.py-tpl
skeleton_setup/conf/app_template/tests/__init__.py-tpl
skeleton_setup/conf/user_template/__init__.py-tpl
skeleton_setup/conf/user_template/admin.py-tpl
skeleton_setup/conf/user_template/apps.py-tpl
skeleton_setup/conf/user_template/forms.py-tpl
skeleton_setup/conf/user_template/model_managers.py-tpl
skeleton_setup/conf/user_template/models.py-tpl
skeleton_setup/conf/user_template/signals.py-tpl
skeleton_setup/conf/user_template/urls.py-tpl
skeleton_setup/conf/user_template/utils.py-tpl
skeleton_setup/conf/user_template/views.py-tpl
skeleton_setup/conf/user_template/api/__init__.py-tpl
skeleton_setup/conf/user_template/api/urls.py-tpl
skeleton_setup/conf/user_template/api/views.py-tpl
skeleton_setup/conf/user_template/migrations/__init__.py-tpl
